autoextract_poet/__init__.py
autoextract_poet/adapters.py
autoextract_poet/items.py
autoextract_poet/page_inputs.py
autoextract_poet/pages.py
autoextract_poet/util.py
autoextract_poet-0.4.0.dist-info/LICENSE
autoextract_poet-0.4.0.dist-info/METADATA
autoextract_poet-0.4.0.dist-info/WHEEL
autoextract_poet-0.4.0.dist-info/top_level.txt
autoextract_poet-0.4.0.dist-info/RECORD
