Metadata-Version: 2.1
Name: autoextract-poet
Version: 0.4.0
Summary: web-poet definitions for AutoExtract API
Home-page: https://github.com/scrapinghub/autoextract-poet
Author: Zyte Group Ltd
Author-email: info@zyte.com
License: UNKNOWN
Platform: UNKNOWN
Classifier: Development Status :: 3 - Alpha
Classifier: Intended Audience :: Developers
Classifier: License :: OSI Approved :: BSD License
Classifier: Natural Language :: English
Classifier: Operating System :: OS Independent
Classifier: Programming Language :: Python :: 3
Classifier: Programming Language :: Python :: 3.6
Classifier: Programming Language :: Python :: 3.7
Classifier: Programming Language :: Python :: 3.8
Classifier: Programming Language :: Python :: 3.9
License-File: LICENSE
Requires-Dist: attrs
Requires-Dist: itemadapter
Requires-Dist: web-poet
